flask_sn_generator.py
flask_sn_generator-0.1.2.dist-info/AUTHORS.rst
flask_sn_generator-0.1.2.dist-info/LICENSE
flask_sn_generator-0.1.2.dist-info/METADATA
flask_sn_generator-0.1.2.dist-info/WHEEL
flask_sn_generator-0.1.2.dist-info/top_level.txt
flask_sn_generator-0.1.2.dist-info/RECORD
