Metadata-Version: 2.1
Name: flask-sn-generator
Version: 0.1.2
Summary: generate global unique increased serial number
Home-page: https://github.com/juforg/flask-sn-generator
Author: juforg
Author-email: juforg@gmail.com
License: MIT license
Keywords: flask_sn_generator
Platform: UNKNOWN
Classifier: Development Status :: 3 - Alpha
Classifier: Intended Audience :: Developers
Classifier: License :: OSI Approved :: MIT License
Classifier: Natural Language :: English
Classifier: Natural Language :: Chinese (Simplified)
Classifier: Environment :: Plugins
Classifier: Framework :: Flask
Classifier: Programming Language :: Python :: 3
Classifier: Programming Language :: Python :: 3.7
Classifier: Programming Language :: Python :: 3.8
Classifier: Programming Language :: Python :: 3.9
Classifier: Topic :: Internet :: WWW/HTTP :: Dynamic Content
Classifier: Topic :: Software Development :: Libraries :: Python Modules
Classifier: Operating System :: Microsoft :: Windows
Classifier: Operating System :: POSIX :: Linux
Classifier: Operating System :: POSIX
Classifier: Operating System :: Unix
Classifier: Operating System :: MacOS
Requires-Dist: flask
Requires-Dist: flask-redis (>=0.4.0)
